cellshape_cluster/__init__.py
cellshape_cluster/check_tolerance.py
cellshape_cluster/clustering_layer.py
cellshape_cluster/deep_embedded_clustering.py
cellshape_cluster/distributions.py
cellshape_cluster/kmeans.py
cellshape_cluster/lightning_deep_embedded_clustering.py
cellshape_cluster/reports.py
cellshape_cluster/training_functions.py
tests/__init__.py
tests/test_integration/__init__.py
tests/test_unit/__init__.py
tests/test_unit/test_placeholder.py
cellshape_cluster-0.0.20.dist-info/LICENSE
cellshape_cluster-0.0.20.dist-info/METADATA
cellshape_cluster-0.0.20.dist-info/WHEEL
cellshape_cluster-0.0.20.dist-info/top_level.txt
cellshape_cluster-0.0.20.dist-info/RECORD
